span_tree/__init__.py
span_tree/api.py
span_tree/call_location.py
span_tree/constants.py
span_tree/handler.py
span_tree/log_span.py
span_tree/log_trace.py
span_tree/log_trace_publisher.py
span_tree/py.typed
span_tree/rich_rendering.py
span_tree-0.0.4.dist-info/METADATA
span_tree-0.0.4.dist-info/WHEEL
span_tree-0.0.4.dist-info/namespace_packages.txt
span_tree-0.0.4.dist-info/top_level.txt
span_tree-0.0.4.dist-info/RECORD
