Metadata-Version: 2.1
Name: span-tree
Version: 0.0.4
Summary: Use trees, traces, and spans and never read a log message again!
Author: Espen Albert
License: MIT
Project-URL: Source, https://github.com/EspenAlbert/py-libs/tree/main/span_tree
Project-URL: Documentation, https://espenalbert.github.io/py-libs/span_tree
Classifier: Programming Language :: Python :: 3.11
Classifier: Development Status :: 2 - Pre-Alpha
Requires-Python: ==3.11.*
Requires-Dist: rich (==13.5.2)
Requires-Dist: typing-extensions (>=4.3.0)
Requires-Dist: zero-3rdparty (==0.0.28)
